arclet/alconna/ichika/__init__.py
arclet/alconna/ichika/adapter.py
arclet/alconna/ichika/typings.py
arclet_alconna_ichika-0.17.3.dist-info/METADATA
arclet_alconna_ichika-0.17.3.dist-info/WHEEL
arclet_alconna_ichika-0.17.3.dist-info/licenses/LICENSE
arclet_alconna_ichika-0.17.3.dist-info/RECORD
